{
 "_definition": "'top' = operator's best realistic bid (<=2x floor) >= best competing collection-wide bid (<=2x floor). For the trait bot this compares a trait-specific bid to collection-wide demand, so 'not top' often just means a competitor posted a higher collection-wide offer, not that the operator was out-bid on its actual trait. Most meaningful for the item bot on pudgypenguins.",
 "by_collection": {
  "pudgypenguins": {
   "snaps_with_our_bid": 153,
   "pct_we_are_top": 0.0,
   "median_gap_below_top_pct_floor": 50.68,
   "p90_gap_below_top_pct_floor": 69.57
  },
  "clonex": {
   "snaps_with_our_bid": 153,
   "pct_we_are_top": 0.0,
   "median_gap_below_top_pct_floor": 81.72,
   "p90_gap_below_top_pct_floor": 84.82
  },
  "lilpudgys": {
   "snaps_with_our_bid": 150,
   "pct_we_are_top": 0.0,
   "median_gap_below_top_pct_floor": 9.38,
   "p90_gap_below_top_pct_floor": 19.96
  },
  "doodles-official": {
   "snaps_with_our_bid": 150,
   "pct_we_are_top": 61.3,
   "median_gap_below_top_pct_floor": 86.86,
   "p90_gap_below_top_pct_floor": 88.87
  },
  "azuki": {
   "snaps_with_our_bid": 147,
   "pct_we_are_top": 68.7,
   "median_gap_below_top_pct_floor": 88.75,
   "p90_gap_below_top_pct_floor": 91.11
  },
  "otherside-koda": {
   "snaps_with_our_bid": 45,
   "pct_we_are_top": 26.7,
   "median_gap_below_top_pct_floor": 0.13,
   "p90_gap_below_top_pct_floor": 0.65
  }
 },
 "by_kind": {
  "item": {
   "snaps": 153,
   "pct_top": 0.0
  },
  "trait": {
   "snaps": 645,
   "pct_top": 31.8
  }
 }
}